tinta/__init__.py
tinta/__main__.py
tinta/colors.ini
tinta/discover.py
tinta/tinta.py
tinta-0.1.5b3.dist-info/METADATA
tinta-0.1.5b3.dist-info/WHEEL
tinta-0.1.5b3.dist-info/licenses/LICENSE
tinta-0.1.5b3.dist-info/RECORD
