Metadata-Version: 2.1
Name: tinta
Version: 0.1.5b3
Summary: Tinta, a magical console output tool.
Project-URL: homepage, https://github.com/brandonscript/tinta
Project-URL: repository, https://github.com/brandonscript/tinta
Author-email: Brandon Shelley <brandon@pacificaviator.co>
License-Expression: MIT
License-File: LICENSE
Keywords: ansi,colors,console,development,print,terminal
Classifier: Development Status :: 4 - Beta
Classifier: Environment :: Console
Classifier: Intended Audience :: Developers
Classifier: License :: OSI Approved :: MIT License
Classifier: Programming Language :: Python :: 3.6
Classifier: Programming Language :: Python :: 3.7
Classifier: Programming Language :: Python :: 3.8
Classifier: Programming Language :: Python :: 3.9
Classifier: Programming Language :: Python :: 3.10
Classifier: Programming Language :: Python :: 3.11
Classifier: Topic :: Utilities
